wdata/__init__.py
wdata/__init__.py.orig
wdata/io.py
wdata/utils.py
wdata-0.2.0.dist-info/LICENSE
wdata-0.2.0.dist-info/METADATA
wdata-0.2.0.dist-info/WHEEL
wdata-0.2.0.dist-info/RECORD
