Metadata-Version: 2.1
Name: wdata
Version: 0.2.0
Summary: W-Data format for superfluid dynamics and the W-SLDA Toolkit.
License: MIT
Author: Michael McNeil Forbes
Author-email: mforbes@alum.mit.edu
Requires-Python: >=3.8,<3.13
Classifier: Development Status :: 3 - Alpha
Classifier: Intended Audience :: Science/Research
Classifier: License :: OSI Approved :: MIT License
Classifier: Programming Language :: Python :: 3
Classifier: Programming Language :: Python :: 3.8
Classifier: Programming Language :: Python :: 3.9
Classifier: Programming Language :: Python :: 3.10
Classifier: Programming Language :: Python :: 3.11
Classifier: Topic :: Scientific/Engineering :: Physics
Classifier: Topic :: Scientific/Engineering :: Visualization
Requires-Dist: numpy (>=1.19.4) ; python_version < "3.8"
Requires-Dist: numpy (>=1.23.4) ; python_version >= "3.8"
Requires-Dist: numpy (>=1.26.4) ; python_version >= "3.12"
Requires-Dist: pytz (>=2020.4)
Requires-Dist: tzlocal (>=2.1)
Requires-Dist: zope.interface (>=5.2.0)
Project-URL: Bug Reports, https://hg.iscimath.org/forbes-group/wdata/issues
Project-URL: Funding, https://www.nsf.gov/awardsearch/showAward?AWD_ID=1707691
Project-URL: Source, https://hg.iscimath.org/forbes-group/wdata
Project-URL: W-SLDA, https://wslda.fizyka.pw.edu.pl
